blacklist/__init__.py
blacklist/base.py
blacklist/utilities.py
flask_blacklist/__init__.py
flask_blacklist/base.py
flask_blacklist/utilities.py
flask_blacklist-0.0.1.dist-info/LICENSE.txt
flask_blacklist-0.0.1.dist-info/METADATA
flask_blacklist-0.0.1.dist-info/WHEEL
flask_blacklist-0.0.1.dist-info/top_level.txt
flask_blacklist-0.0.1.dist-info/RECORD
