Metadata-Version: 2.1
Name: flask_blacklist
Version: 0.0.1
Summary: Token blacklist flask extension
Home-page: https://github.com/jakkso/flask_blacklist
Author: Alexander Potts
Author-email: alexander@jakkso.com
License: MIT License
Platform: UNKNOWN
Classifier: Programming Language :: Python :: 3
Classifier: License :: OSI Approved :: MIT License
Classifier: Operating System :: OS Independent
Classifier: Framework :: Flask
